dapume/__init__.py
dapume/utils.py
dapume/assets/__init__.py
dapume/assets/absolute_note.py
dapume/assets/chord.py
dapume/assets/chord_typing.py
dapume/assets/constants.py
dapume/assets/linear_score.py
dapume/assets/note_line.py
dapume/assets/relative_note.py
dapume/assets/score_parameters.py
dapume-0.3.1.dist-info/METADATA
dapume-0.3.1.dist-info/WHEEL
dapume-0.3.1.dist-info/licenses/LICENSE
dapume-0.3.1.dist-info/RECORD
