Metadata-Version: 2.4
Name: dapume
Version: 0.3.1
Summary: 打谱么 - 将线性乐谱转换为 MIDI 文件
Project-URL: Homepage, https://github.com/ScarlettRinko/dapume
Project-URL: Repository, https://github.com/ScarlettRinko/dapume
Project-URL: Issues, https://github.com/ScarlettRinko/dapume/issues
Author-email: ScarlettRinko <pleasantgoat2@yeah.net>
License-File: LICENSE
Keywords: linear-score,midi,music,renderer,score
Classifier: Development Status :: 3 - Alpha
Classifier: Intended Audience :: Developers
Classifier: License :: OSI Approved :: MIT License
Classifier: Programming Language :: Python :: 3
Classifier: Programming Language :: Python :: 3.8
Classifier: Programming Language :: Python :: 3.9
Classifier: Programming Language :: Python :: 3.10
Classifier: Programming Language :: Python :: 3.11
Classifier: Programming Language :: Python :: 3.12
Classifier: Topic :: Multimedia :: Sound/Audio :: MIDI
Classifier: Topic :: Software Development :: Libraries :: Python Modules
Requires-Python: >=3.8
Requires-Dist: mido>=1.2.0
